friendly_pandas/__init__.py
friendly_pandas/generic.py
friendly_pandas/specific/__init__.py
friendly_pandas/specific/key_error.py
friendly_pandas/specific/setting_with_copy_warning.py
friendly_pandas-0.1.3.dist-info/LICENSE
friendly_pandas-0.1.3.dist-info/METADATA
friendly_pandas-0.1.3.dist-info/WHEEL
friendly_pandas-0.1.3.dist-info/top_level.txt
friendly_pandas-0.1.3.dist-info/RECORD
