Metadata-Version: 2.1
Name: friendly-pandas
Version: 0.1.3
Summary: Friendly tracebacks for Pandas users.
Home-page: https://github.com/friendly-traceback/friendly-pandas
Author: André Roberge
Author-email: Andre.Roberge@gmail.com
Classifier: Development Status :: 1 - Planning
Classifier: Environment :: Console
Classifier: License :: OSI Approved :: MIT License
Classifier: Natural Language :: English
Classifier: Programming Language :: Python :: 3
Classifier: Programming Language :: Python :: 3.8
Classifier: Programming Language :: Python :: 3.9
Classifier: Programming Language :: Python :: 3.10
Classifier: Intended Audience :: Education
Classifier: Intended Audience :: Science/Research
Classifier: Topic :: Education
Classifier: Topic :: Scientific/Engineering
Requires-Python: >=3.8
License-File: LICENSE
Requires-Dist: friendly-traceback (>=0.7.47)
Requires-Dist: pandas (>=1.4)
